info_chunks_to_embeddings.py
info_chunks_to_embeddings-1.0.1.dist-info/METADATA
info_chunks_to_embeddings-1.0.1.dist-info/WHEEL
info_chunks_to_embeddings-1.0.1.dist-info/entry_points.txt
info_chunks_to_embeddings-1.0.1.dist-info/top_level.txt
info_chunks_to_embeddings-1.0.1.dist-info/RECORD
