Metadata-Version: 2.1
Name: info-chunks-to-embeddings
Version: 1.0.1
Requires-Dist: torch
Requires-Dist: sentence-transformers
Requires-Dist: argparse
